<?xml version="1.0" encoding="UTF-8"?>
<Students>
    <Student Roll_no="1" Name="John Doe" Marks="85" Rank="1" Result="dist" />
    <Student Roll_no="2" Name="Jane Doe" Marks="75" Rank="2" Result="first" />
    <Student Roll_no="3" Name="Bob Smith" Marks="60" Rank="4" Result="first" />
    <Student Roll_no="4" Name="Alice Johnson" Marks="50" Rank="6" Result="second" />
    <Student Roll_no="5" Name="Dave Williams" Marks="45" Rank="9" Result="second" />
    <Student Roll_no="6" Name="Susan Brown" Marks="40" Rank="12" Result="second" />
    <Student Roll_no="7" Name="Mike Davis" Marks="35" Rank="15" Result="fail" />
    <Student Roll_no="8" Name="Jim Miller" Marks="30" Rank="18" Result="fail" />
    <Student Roll_no="9" Name="Judy Green" Marks="25" Rank="21" Result="fail" />
    <Student Roll_no="10" Name="Mark White" Marks="20" Rank="24" Result="fail" />
</Students>